{
  "span_128_dtype_bf16": {
    "span": "128",
    "dtype": "bf16",
    "max_abs_diff": {
      "max": 0.0,
      "mean": 0.0,
      "p95": 0.0
    },
    "p99_abs_diff": {
      "max": 0.0,
      "mean": 0.0
    },
    "top1_agreement": {
      "min": 1.0,
      "mean": 1.0
    },
    "sample_count": 3
  },
  "span_128_dtype_fp16": {
    "span": "128",
    "dtype": "fp16",
    "max_abs_diff": {
      "max": 0.0,
      "mean": 0.0,
      "p95": 0.0
    },
    "p99_abs_diff": {
      "max": 0.0,
      "mean": 0.0
    },
    "top1_agreement": {
      "min": 1.0,
      "mean": 1.0
    },
    "sample_count": 3
  },
  "span_32_dtype_bf16": {
    "span": "32",
    "dtype": "bf16",
    "max_abs_diff": {
      "max": 0.0,
      "mean": 0.0,
      "p95": 0.0
    },
    "p99_abs_diff": {
      "max": 0.0,
      "mean": 0.0
    },
    "top1_agreement": {
      "min": 1.0,
      "mean": 1.0
    },
    "sample_count": 3
  },
  "span_32_dtype_fp16": {
    "span": "32",
    "dtype": "fp16",
    "max_abs_diff": {
      "max": 0.0,
      "mean": 0.0,
      "p95": 0.0
    },
    "p99_abs_diff": {
      "max": 0.0,
      "mean": 0.0
    },
    "top1_agreement": {
      "min": 1.0,
      "mean": 1.0
    },
    "sample_count": 3
  },
  "span_512_dtype_bf16": {
    "span": "512",
    "dtype": "bf16",
    "max_abs_diff": {
      "max": 0.0,
      "mean": 0.0,
      "p95": 0.0
    },
    "p99_abs_diff": {
      "max": 0.0,
      "mean": 0.0
    },
    "top1_agreement": {
      "min": 1.0,
      "mean": 1.0
    },
    "sample_count": 3
  },
  "span_512_dtype_fp16": {
    "span": "512",
    "dtype": "fp16",
    "max_abs_diff": {
      "max": 0.0,
      "mean": 0.0,
      "p95": 0.0
    },
    "p99_abs_diff": {
      "max": 0.0,
      "mean": 0.0
    },
    "top1_agreement": {
      "min": 1.0,
      "mean": 1.0
    },
    "sample_count": 3
  }
}